seabird_processing/__init__.py
seabird_processing/batch.py
seabird_processing/commands.py
seabird_processing/configs.py
seabird_processing/logger.py
seabird_processing/settings.py
seabird_processing-0.2.0.dist-info/LICENSE
seabird_processing-0.2.0.dist-info/WHEEL
seabird_processing-0.2.0.dist-info/METADATA
seabird_processing-0.2.0.dist-info/RECORD
