Metadata-Version: 2.1
Name: seabird-processing
Version: 0.2.0
Summary: Python interface for calling Seabird CTD processing commands
License: MIT
Author: Taylor Denouden
Author-email: taylor.denouden@hakai.org
Requires-Python: >=3.9,<4.0
Classifier: License :: OSI Approved :: MIT License
Classifier: Programming Language :: Python :: 3
Classifier: Programming Language :: Python :: 3.9
Classifier: Programming Language :: Python :: 3.10
Classifier: Programming Language :: Python :: 3.11
Requires-Dist: pydantic (>=2.1.1,<3.0.0)
Requires-Dist: pydantic-settings (>=2.0.2,<3.0.0)
